intervalsicu/__init__.py
intervalsicu/api/__init__.py
intervalsicu/api/activity.py
intervalsicu/api/calendar.py
intervalsicu/api/error.py
intervalsicu/api/event.py
intervalsicu/api/intervals.py
intervalsicu/api/intervals_object.py
intervalsicu/api/wellness.py
intervalsicu/api/workout.py
intervalsicu-0.1.4.dist-info/LICENSE
intervalsicu-0.1.4.dist-info/METADATA
intervalsicu-0.1.4.dist-info/WHEEL
intervalsicu-0.1.4.dist-info/top_level.txt
intervalsicu-0.1.4.dist-info/RECORD
