Metadata-Version: 2.1
Name: intervalsicu
Version: 0.1.4
Summary: A basic interface to the Intervals.icu system
Home-page: https://github.com/rday/py-intervalsicu
Author: Ryan Day
Author-email: ryanday2@gmail.com
Project-URL: Bug Tracker, https://github.com/rday/py-intervalsicu
Classifier: Programming Language :: Python :: 3
Classifier: License :: OSI Approved :: MIT License
Classifier: Operating System :: OS Independent
Requires-Python: >=3.6
License-File: LICENSE
Requires-Dist: requests (>=2.28.1)
Requires-Dist: pytest (==6.2.2)
